sg_games/XOX_game.py
sg_games/__init__.py
sg_games/__main__.py
sg_games/brickbreaker_game.py
sg_games/click_a_dot.py
sg_games/flappy_bird.py
sg_games/peg_game.py
sg_games/pingpong_game.py
sg_games/snake_game.py
sg_games-0.1.5.dist-info/licenses/LICENSE
sg_games-0.1.5.dist-info/METADATA
sg_games-0.1.5.dist-info/WHEEL
sg_games-0.1.5.dist-info/entry_points.txt
sg_games-0.1.5.dist-info/top_level.txt
sg_games-0.1.5.dist-info/RECORD
