Metadata-Version: 2.4
Name: sg-games
Version: 0.1.5
Summary: A small games package
Home-page: https://github.com/BHuvaneshwarMarri/sg_games
Author: Marri Bhuvaneshwar
Author-email: Marri Bhuvaneshwar <bhuvaneshwarmarri@gmail.com>
License-Expression: MIT
Project-URL: Homepage, https://github.com/BhuvaneshwarMarri/sg-games
Project-URL: Issues, https://github.com/BhuvaneshwarMarri/sg-games/issues
Classifier: Programming Language :: Python :: 3
Classifier: Operating System :: OS Independent
Classifier: Environment :: X11 Applications
Classifier: Topic :: Games/Entertainment :: Arcade
Requires-Python: >=3.9
License-File: LICENSE
Dynamic: license-file
